LICENSE
README.md
pyproject.toml
setup.cfg
setup.py
openaipro/__init__.py
openaipro/_openai_scripts.py
openaipro/api_requestor.py
openaipro/cli.py
openaipro/datalib.py
openaipro/embeddings_utils.py
openaipro/error.py
openaipro/object_classes.py
openaipro/openai_object.py
openaipro/openai_response.py
openaipro/upload_progress.py
openaipro/util.py
openaipro/validators.py
openaipro/version.py
openaipro/wandb_logger.py
openaipro.egg-info/PKG-INFO
openaipro.egg-info/SOURCES.txt
openaipro.egg-info/dependency_links.txt
openaipro.egg-info/entry_points.txt
openaipro.egg-info/requires.txt
openaipro.egg-info/top_level.txt
openaipro.egg-info/zip-safe
openaipro/api_resources/__init__.py
openaipro/api_resources/completion.py
openaipro/api_resources/customer.py
openaipro/api_resources/deployment.py
openaipro/api_resources/edit.py
openaipro/api_resources/embedding.py
openaipro/api_resources/engine.py
openaipro/api_resources/error_object.py
openaipro/api_resources/file.py
openaipro/api_resources/fine_tune.py
openaipro/api_resources/image.py
openaipro/api_resources/model.py
openaipro/api_resources/moderation.py
openaipro/api_resources/abstract/__init__.py
openaipro/api_resources/abstract/api_resource.py
openaipro/api_resources/abstract/createable_api_resource.py
openaipro/api_resources/abstract/deletable_api_resource.py
openaipro/api_resources/abstract/engine_api_resource.py
openaipro/api_resources/abstract/listable_api_resource.py
openaipro/api_resources/abstract/nested_resource_class_methods.py
openaipro/api_resources/abstract/updateable_api_resource.py
openaipro/api_resources/experimental/__init__.py
openaipro/api_resources/experimental/completion_config.py
openaipro/tests/__init__.py
openaipro/tests/test_api_requestor.py
openaipro/tests/test_endpoints.py
openaipro/tests/test_exceptions.py
openaipro/tests/test_file_cli.py
openaipro/tests/test_long_examples_validator.py
openaipro/tests/test_url_composition.py
openaipro/tests/test_util.py
openaipro/tests/asyncio/__init__.py
openaipro/tests/asyncio/test_endpoints.py