Metadata-Version: 2.1
Name: openaipro
Version: 0.26.5
Summary: Python client library for the OpenAI API
Home-page: https://github.com/tedxnet/python-openai
Author: OpenAI
Author-email: support@openai.com
Classifier: Programming Language :: Python :: 3
Classifier: License :: OSI Approved :: MIT License
Classifier: Operating System :: OS Independent
Requires-Python: >=3.7.1
Provides-Extra: dev
Provides-Extra: datalib
Provides-Extra: wandb
Provides-Extra: embeddings
License-File: LICENSE
